moltransform/__init__.py
moltransform/io.py
moltransform/transform.py
moltransform-0.1.3.dist-info/WHEEL
moltransform-0.1.3.dist-info/METADATA
moltransform-0.1.3.dist-info/RECORD
