Metadata-Version: 2.1
Name: moltransform
Version: 0.1.3
Summary: 
Home-page: https://github.com/RodolfoFerro/moltransform
License: MIT
Keywords: Rigid transformations,Molecular coordinates,xyz files
Author: Rodolfo Ferro
Author-email: rodolfoferroperez@gmail.com
Requires-Python: >=3.6,<4.0
Classifier: License :: OSI Approved :: MIT License
Classifier: Operating System :: OS Independent
Classifier: Programming Language :: Python :: 3
Classifier: Programming Language :: Python :: 3.6
Classifier: Programming Language :: Python :: 3.7
Requires-Dist: numpy (>=1.16,<2.0)
Project-URL: Repository, https://github.com/RodolfoFerro/moltransform
